coin_clip/__init__.py
coin_clip/__version__.py
coin_clip/base_model.py
coin_clip/chroma_embedding.py
coin_clip/cli.py
coin_clip/coinclip.py
coin_clip/consts.py
coin_clip/detect.py
coin_clip/utils.py
coin_clip-0.1.dist-info/METADATA
coin_clip-0.1.dist-info/WHEEL
coin_clip-0.1.dist-info/entry_points.txt
coin_clip-0.1.dist-info/top_level.txt
coin_clip-0.1.dist-info/RECORD
